MANIFEST.in
setup.cfg
setup.py
tw2/__init__.py
tw2.jqplugins.tagify.egg-info/PKG-INFO
tw2.jqplugins.tagify.egg-info/SOURCES.txt
tw2.jqplugins.tagify.egg-info/dependency_links.txt
tw2.jqplugins.tagify.egg-info/entry_points.txt
tw2.jqplugins.tagify.egg-info/namespace_packages.txt
tw2.jqplugins.tagify.egg-info/not-zip-safe
tw2.jqplugins.tagify.egg-info/requires.txt
tw2.jqplugins.tagify.egg-info/top_level.txt
tw2/jqplugins/__init__.py
tw2/jqplugins/tagify/__init__.py
tw2/jqplugins/tagify/samples.py
tw2/jqplugins/tagify/widgets.py
tw2/jqplugins/tagify/static/jquery.tagify.js
tw2/jqplugins/tagify/static/tagify.css
tw2/jqplugins/tagify/templates/__init__.py
tw2/jqplugins/tagify/templates/tagbox.mak