Metadata-Version: 1.0
Name: tw2.jqplugins.tagify
Version: 2.0b1dev-20110719
Summary: Tagify for ToscaWidgets2
Home-page: https://github.com/gregjurman/tw2.jqplugins.tagify/
Author: Greg Jurman
Author-email: gdj2214@rit.edu
License: UNKNOWN
Keywords: toscawidgets.widgets
Platform: UNKNOWN
Classifier: Development Status :: 3 - Alpha
Classifier: Environment :: Web Environment
Classifier: Environment :: Web Environment :: ToscaWidgets
Classifier: Topic :: Software Development :: Libraries :: Python Modules
Classifier: Topic :: Software Development :: Widget Sets
Classifier: Intended Audience :: Developers
Classifier: Operating System :: OS Independent
Classifier: Programming Language :: Python
